README.rst
setup.py
wheelr/__init__.py
wheelr/codes.py
wheelr/dictconfig.py
wheelr/logger.py
wheelr/six.py
wheelr/utils.py
wheelr/wheelr.py
wheelr.egg-info/PKG-INFO
wheelr.egg-info/SOURCES.txt
wheelr.egg-info/dependency_links.txt
wheelr.egg-info/entry_points.txt
wheelr.egg-info/requires.txt
wheelr.egg-info/top_level.txt