Metadata-Version: 1.0
Name: wheelr
Version: 0.1
Summary: Creates Python Wheel Archives.
Home-page: https://github.com/cloudify-cosmo/wheelr
Author: Gigaspaces
Author-email: cosmo-admin@gigaspaces.com
License: LICENSE
Platform: All
